src/sync_fifo.v
module sync_fifo #(
    parameter DATA_WIDTH=8,
    parameter DEPTH=8
)(
    input wire clk,
    input wire reset,
    input wire wr_en,
    input wire rd_en,
    input wire [DATA_WIDTH-1:0] data_in,
    
    output reg [DATA_WIDTH-1:0] data_out,
    output wire full,
    output wire empty
);
    // FIFO memory
    reg [DATA_WIDTH-1:0] memory [0:DEPTH-1];

    // Number of bits required to address FIFO locations
    localparam ADDR_WIDTH = $clog2(DEPTH);

    // Read and write pointers
    reg [ADDR_WIDTH-1:0] wr_ptr;
    reg [ADDR_WIDTH-1:0] rd_ptr;

    // Number of valid entries currently stored
    reg [ADDR_WIDTH:0] count;

    // FIFO status flags
    assign empty = (count == 0);
    assign full  = (count == DEPTH);

    // Sequential logic
    always @(posedge clk) begin
        if (reset) begin
            wr_ptr   <= 0;
            rd_ptr   <= 0;
            count    <= 0;
            data_out <= 0;
        end
        
        else begin
            
            // Write operation
            if (wr_en && !full) begin
                memory[wr_ptr] <= data_in;
                wr_ptr <= wr_ptr + 1'b1;
            end
        

            // Read operation
             if (rd_en && !empty) begin
                data_out <= memory[rd_ptr];
                rd_ptr <= rd_ptr + 1'b1;
            end

            // Update FIFO count
             case ({wr_en && !full, rd_en && !empty})
             2'b10: count <= count + 1'b1;  // Write only
             2'b01: count <= count - 1'b1;  // Read only
             2'b11: count <= count;         // Write and read
             2'b00: count <= count;         // No operation
             endcase
             
        end
    end
endmodule

tb/sync_fifo_tb.v
`timescale 1ns/1ps

module sync_fifo_tb;

    parameter DATA_WIDTH = 8;
    parameter DEPTH = 8;

    //loop variable for testing
    integer i;
    
    // Testbench signals
    reg clk;
    reg reset;
    reg wr_en;
    reg rd_en;
    reg [DATA_WIDTH-1:0] data_in;

    wire [DATA_WIDTH-1:0] data_out;
    wire full;
    wire empty;

    // Instantiate the Design Under Test (DUT)
    sync_fifo #(
        .DATA_WIDTH(DATA_WIDTH),
        .DEPTH(DEPTH)
    ) dut (
        .clk(clk),
        .reset(reset),
        .wr_en(wr_en),
        .rd_en(rd_en),
        .data_in(data_in),
        .data_out(data_out),
        .full(full),
        .empty(empty)
    );

     // Clock generation
    initial begin
        clk = 0;
        forever #5 clk = ~clk;
    end

    // Generate waveform file for GTKWave
    initial begin
        $dumpfile("waveform/fifo_wave.vcd");
        $dumpvars(0, sync_fifo_tb);
    end

    // Reset and initial input signals
    initial begin
        reset   = 1;
        wr_en   = 0;
        rd_en   = 0;
        data_in = 0;
        #12;
        reset = 0;
        
        // Write 10 into FIFO
        @(negedge clk);
        wr_en = 1;
        data_in = 8'd10;

        // Write 20 into FIFO
        @(negedge clk);
        data_in = 8'd20;

        // Write 30 into FIFO
        @(negedge clk);
        data_in = 8'd30;

        // Stop writing
        @(negedge clk);
        wr_en = 0;

        // Start reading from FIFO
        rd_en = 1;

        // Read first value
        @(posedge clk);
        #1;
        $display("Read 1 = %d", data_out);

        // Read second value
        @(posedge clk);
        #1;
        $display("Read 2 = %d", data_out);

        // Read third value
        @(posedge clk);
        #1;
        $display("Read 3 = %d", data_out);

        // Stop reading
        @(negedge clk);
        rd_en = 0;

        // Wait before starting FULL test
        #10;

        // Fill FIFO with 8 values
        $display("Starting FULL condition test");

        for (i = 0; i < DEPTH; i = i + 1) begin
            @(negedge clk);
            wr_en = 1;
            data_in = (i + 1) * 10;
        end

        // Stop writing
        @(negedge clk);
        wr_en = 0;

        // Allow signals to settle
        #1;

        // Check FULL flag and occupancy
        if (full == 1'b1 && empty == 1'b0 && dut.count == DEPTH)
            $display("PASS: FIFO FULL condition detected");
        else
            $display("FAIL: FIFO FULL condition incorrect");

        // Test overflow protection
        $display("Starting OVERFLOW protection test");

        // Attempt to write 90 when FIFO is already full
        @(negedge clk);
        wr_en = 1;
        data_in = 8'd90;

        // Wait for the next rising edge
        @(posedge clk);
        #1;

        // Check that FIFO remains full
        if (full == 1'b1 && dut.count == DEPTH)
            $display("PASS: Overflow write blocked");
        else
            $display("FAIL: Overflow protection failed");

        // Stop writing
        @(negedge clk);
        wr_en = 0;
        
    
        // Test EMPTY condition
        $display("Starting EMPTY condition test");

        // Read all 8 stored values
        for (i = 0; i < DEPTH; i = i + 1) begin
            @(negedge clk);
            rd_en = 1;

             @(posedge clk);
            #1;

            if (data_out === (i + 1) * 10)
                $display("PASS: Read value %0d", data_out);
            else
                $display("FAIL: Expected %0d, got %0d",
                    (i + 1) * 10, data_out);
        end

        // Stop reading
        @(negedge clk);
        rd_en = 0;
        #1;

        // Check EMPTY condition
        if (empty == 1'b1 && full == 1'b0 && dut.count == 0)
            $display("PASS: FIFO EMPTY condition detected");
        else
            $display("FAIL: FIFO EMPTY condition incorrect");

        // Test UNDERFLOW protection
        $display("Starting UNDERFLOW protection test");

        // Attempt one more read while empty
        @(negedge clk);
        rd_en = 1;
 
        @(posedge clk);
        #1;

        // Read pointer and count should remain unchanged
        if (empty == 1'b1 && dut.count == 0 && dut.rd_ptr == 3)
             $display("PASS: Underflow read blocked");
        else
            $display("FAIL: Underflow protection failed");

        // Stop reading
        @(negedge clk);
        rd_en = 0;

        // =======================================
        // SIMULTANEOUS READ AND WRITE TEST
        // =======================================
        
        $display("Starting SIMULTANEOUS READ/WRITE test");
        // First write 10 into the empty FIFO
        @(negedge clk);
        wr_en = 1;
        rd_en = 0;
        data_in = 8'd10;

        // Allow the write at the next rising edge
        @(posedge clk);
        #1;

        // Enable both read and write
        @(negedge clk);
        wr_en = 1;
        rd_en = 1;
        data_in = 8'd20;

        // Perform both operations on the next rising edge
        @(posedge clk);
        #1;

        // Debug simultaneous READ/WRITE
        $display("DEBUG: data_out = %0d", data_out);
        $display("DEBUG: count = %0d", dut.count);
        $display("DEBUG: wr_ptr = %0d", dut.wr_ptr);
        $display("DEBUG: rd_ptr = %0d", dut.rd_ptr);

        // Check simultaneous READ/WRITE
        if (data_out === 8'd10 &&
            dut.count == 1 &&
            dut.wr_ptr == 5 &&
            dut.rd_ptr == 4)
            $display("PASS: Simultaneous READ/WRITE");
        else
            $display("FAIL: Simultaneous READ/WRITE");

        // Stop both operations
        @(negedge clk);
        wr_en = 0;
        rd_en = 0;

        // Verify remaining value after simultaneous operation
        $display("Checking remaining FIFO data");

        @(negedge clk);
        rd_en = 1;

        @(posedge clk);
        #1;

        if (data_out === 8'd20 && empty == 1'b1 && dut.count == 0)
            $display("PASS: Remaining value 20 read correctly");
        else
            $display("FAIL: Remaining value verification");

        // Stop reading
        @(negedge clk);
        rd_en = 0;

        // End simulation
        #10;
        $finish;
   
    end
    
endmodule

waveform/fifo_wave.vcd
$date
	Thu Oct 08 14:54:55 2026
$end
$version
	Icarus Verilog
$end
$timescale
	1ps
$end
$scope module sync_fifo_tb $end
$var wire 1 ! full $end
$var wire 1 " empty $end
$var wire 8 # data_out [7:0] $end
$var reg 1 $ clk $end
$var reg 8 % data_in [7:0] $end
$var reg 1 & rd_en $end
$var reg 1 ' reset $end
$var reg 1 ( wr_en $end
$var integer 32 ) i [31:0] $end
$scope module dut $end
$var wire 1 $ clk $end
$var wire 8 * data_in [7:0] $end
$var wire 1 & rd_en $end
$var wire 1 ' reset $end
$var wire 1 ( wr_en $end
$var wire 1 ! full $end
$var wire 1 " empty $end
$var reg 4 + count [3:0] $end
$var reg 8 , data_out [7:0] $end
$var reg 3 - rd_ptr [2:0] $end
$var reg 3 . wr_ptr [2:0] $end
$upscope $end
$upscope $end
$enddefinitions $end
#0
$dumpvars
bx .
bx -
bx ,
bx +
b0 *
bx )
0(
1'
0&
b0 %
0$
bx #
x"
x!
$end
#5000
b0 #
b0 ,
1"
0!
b0 +
b0 -
b0 .
1$
#10000
0$
#12000
0'
#15000
1$
#20000
b1010 %
b1010 *
1(
0$
#25000
0"
b1 +
b1 .
1$
#30000
b10100 %
b10100 *
0$
#35000
b10 +
b10 .
1$
#40000
b11110 %
b11110 *
0$
#45000
b11 +
b11 .
1$
#50000
1&
0(
0$
#55000
b10 +
b1 -
b1010 #
b1010 ,
1$
#60000
0$
#65000
b1 +
b10 -
b10100 #
b10100 ,
1$
#70000
0$
#75000
1"
b0 +
b11 -
b11110 #
b11110 ,
1$
#80000
0&
0$
#85000
1$
#90000
b1010 %
b1010 *
1(
0$
b1 )
#95000
0"
b1 +
b100 .
1$
#100000
b10 )
b10100 %
b10100 *
0$
#105000
b10 +
b101 .
1$
#110000
b11 )
b11110 %
b11110 *
0$
#115000
b11 +
b110 .
1$
#120000
b100 )
b101000 %
b101000 *
0$
#125000
b100 +
b111 .
1$
#130000
b101 )
b110010 %
b110010 *
0$
#135000
b101 +
b0 .
1$
#140000
b110 )
b111100 %
b111100 *
0$
#145000
b110 +
b1 .
1$
#150000
b111 )
b1000110 %
b1000110 *
0$
#155000
b111 +
b10 .
1$
#160000
b1000 )
b1010000 %
b1010000 *
0$
#165000
1!
b1000 +
b11 .
1$
#170000
0(
0$
#175000
1$
#180000
b1011010 %
b1011010 *
1(
0$
#185000
1$
#190000
b0 )
0(
0$
#195000
1$
#200000
1&
0$
#205000
0!
b111 +
b100 -
b1010 #
b1010 ,
1$
#206000
b1 )
#210000
0$
#215000
b110 +
b101 -
b10100 #
b10100 ,
1$
#216000
b10 )
#220000
0$
#225000
b101 +
b110 -
b11110 #
b11110 ,
1$
#226000
b11 )
#230000
0$
#235000
b100 +
b111 -
b101000 #
b101000 ,
1$
#236000
b100 )
#240000
0$
#245000
b11 +
b0 -
b110010 #
b110010 ,
1$
#246000
b101 )
#250000
0$
#255000
b10 +
b1 -
b111100 #
b111100 ,
1$
#256000
b110 )
#260000
0$
#265000
b1 +
b10 -
b1000110 #
b1000110 ,
1$
#266000
b111 )
#270000
0$
#275000
1"
b0 +
b11 -
b1010000 #
b1010000 ,
1$
#276000
b1000 )
#280000
0&
0$
#285000
1$
#290000
1&
0$
#295000
1$
#300000
0&
0$
#305000
1$
#310000
b1010 %
b1010 *
1(
0$
#315000
0"
b1 +
b100 .
1$
#320000
b10100 %
b10100 *
1&
0$
#325000
b100 -
b1010 #
b1010 ,
b101 .
1$
#330000
0&
0(
0$
#335000
1$
#340000
1&
0$
#345000
1"
b0 +
b101 -
b10100 #
b10100 ,
1$
#350000
0&
0$
